oricat/__init__.py
oricat/logger.py
oricat-1.0.0.dist-info/LICENSE
oricat-1.0.0.dist-info/METADATA
oricat-1.0.0.dist-info/WHEEL
oricat-1.0.0.dist-info/entry_points.txt
oricat-1.0.0.dist-info/RECORD
