Metadata-Version: 2.1
Name: oricat
Version: 1.0.0
Summary: Categorise images by orientation
Home-page: https://github.com/cliffano/oricat
License: MIT
Keywords: oricat,images,categorise,orientation
Author: Cliffano Subagio
Author-email: cliffano@gmail.com
Requires-Python: >=3.10,<4.0
Classifier: License :: OSI Approved :: MIT License
Classifier: Operating System :: OS Independent
Classifier: Programming Language :: Python :: 3
Classifier: Programming Language :: Python :: 3.10
Classifier: Programming Language :: Python :: 3.11
Classifier: Programming Language :: Python :: 3.12
Requires-Dist: PyYAML (>=6.0.1,<7.0.0)
Requires-Dist: click (==8.1.7)
Requires-Dist: conflog (>=1.5.1,<2.0.0)
Requires-Dist: pillow (>=10.3.0,<11.0.0)
Project-URL: Documentation, https://github.com/cliffano/oricat
Project-URL: Repository, https://github.com/cliffano/oricat
